{"BaseModel.ea923ec2-36e6-4258-a91b-97b4475bad9f": {"id": "ea923ec2-36e6-4258-a91b-97b4475bad9f", "created_at": "2023-02-12T09:24:07.304461", "updated_at": "2023-02-12T09:24:07.304531", "name": "My First Model", "my_number": 89, "__class__": "BaseModel"}, "BaseModel.794f82d3-8875-4ce9-9502-3cb8d4f84c05": {"id": "794f82d3-8875-4ce9-9502-3cb8d4f84c05", "created_at": "2023-02-12T09:27:52.529141", "updated_at": "2023-02-12T09:27:52.529228", "name": "My First Model", "my_number": 89, "__class__": "BaseModel"}, "BaseModel.aceb47e5-2df4-4e10-9863-5da43ea3b9a3": {"id": "aceb47e5-2df4-4e10-9863-5da43ea3b9a3", "created_at": "2023-02-12T09:28:18.759041", "updated_at": "2023-02-12T09:28:18.759172", "name": "My First Model", "my_number": 89, "__class__": "BaseModel"}}